{
       "Source": "hirunews",
       "Timestamp": "Wednesday, 13 October 2021 - 7:48",
       "Headline": "එක්ස්ප්‍රස් පර්ල් ගැන පරිසරවේදීන් අනතුරු අඟවයි",
       "News Content": "කොළඹ වරායට ආසන්න මුහුදු කලාපයේදී ගිනි ගැනීමට ලක්ව ගිලී පවතින එක්ස්ප්‍රස් පර්ල් නෞකාවෙන් මෙරට පරිසර පද්ධතියට දැඩි අවදානමක් පවතින බව පරිසර සංවිධාන පෙන්වා දෙනවා.\nමේ පිලිබඳව අදහස් දක්වමින් පරිසර යුක්ති කේන්ද්‍රයේ ජ්‍යේෂ්ඨ උපදේශක හේමන්ත විතානගේ සඳහන් කළේ, නෞකාවෙන් සිදු වූ පරිසර හානියට වන්දි ලබා ගැනීමේ කටයුතු සහ අපද්‍රව්‍ය ඉවත් කිරීමේ කටයුතු විධිමත් කළමනාකාරීත්වයකින් සිදු නොවන බවටයි.\nමේ අතර, පරිසර සංවිධාන සහ ධිවර ජනතාව එක්ව මිීගමුව සරක්කුව වෙරළේ ඊයේ විරෝධතාවක් සංවිධාන කර තිබුණා.",
       "URL": "https://www.hirunews.lk/284843/එක්ස්ප්‍රස්-පර්ල්-ගැන-පරිසරවේදීන්-අනතුරු-අඟවයි",
       "Category": "Local News",
       "Parent URL": "https://www.hirunews.lk/local-news.php?pageID=1632"
}