{
       "Source": "hirunews",
       "Timestamp": "Thursday, 12 August 2021 - 11:40",
       "Headline": "සෞඛ්‍ය අමාත්‍යවරිය සහ නිලධාරීන් පිරිසක් ජනපති සමඟ විශේෂ සාකච්ඡාවක",
       "News Content": "සෞඛ්‍ය අමාත්‍ය පවිත්‍රා වන්නිආරච්චි ඇතුළු සෞඛ්‍ය අමාත්‍යාංශයේ ඉහළ නිලධාරීන් පිරිසක් මේ වනවිට ජනාධිපතිවරයා සමඟ විශේෂ සාකච්ඡාවක නිරත වන බවට තොරතුරු වාර්තා වනවා.",
       "URL": "https://www.hirunews.lk/279502/සෞඛ්‍ය-අමාත්‍යවරිය-සහ-නිලධාරීන්-පිරිසක්-ජනපති-සමඟ-විශේෂ-සාකච්ඡාවක",
       "Category": "Local News",
       "Parent URL": "https://www.hirunews.lk/local-news.php?pageID=1759"
}