{
       "Source": "hirunews",
       "Timestamp": "Saturday, 17 July 2021 - 16:54",
       "Headline": "මැණික් හා ස්වර්ණාභරණ අධිකාරියේ ප්‍රධාන කාර්යාලයේ කටයුතු තාවකාලිකව අත්හිටුවයි",
       "News Content": "ගිලා බැසීමේ අවදානමක් හේතුවෙන් කොල්ලුපිටියේ පිහිටි ජාතික මැණික් හා ස්වර්ණාභරණ අධිකාරියේ ප්‍රධාන කාර්යාලයේ සියලු කටයුතු තාවකාලිකව අත්හිටුවා තිබෙනවා.\nඑහි සභාපති තිලක් වීරසිංහ කියා සිටියේ ගොඩනැගිලි පර්යේෂණ සංවිධානයේ නිලධාරින් පැමිණ මහල් 4කින් සමන්විත ගොඩනැගිල්ලෙන් ඉවත් වන ලෙස දැනුම් දුන් බවයි.\nප්‍රධාන කාර්යාලයට යාබදව ඉදිකෙරෙන නව ගොඩනැගිල්ලක ඉදිකිරීම් හේතුවෙන් එය මෙලෙස ගිලා බැසීමේ අවදානමක් මතුව තිබෙනවා.",
       "URL": "https://www.hirunews.lk/277236/මැණික්-හා-ස්වර්ණාභරණ-අධිකාරියේ-ප්‍රධාන-කාර්යාලයේ-කටයුතු-තාවකාලිකව-අත්හිටුවයි",
       "Category": "Local News",
       "Parent URL": "https://www.hirunews.lk/local-news.php?pageID=1814"
}