{
       "Source": "hirunews",
       "Timestamp": "Saturday, 27 March 2021 - 15:38",
       "Headline": "තවත් ආසාදිතයින් 243 දෙනෙකු සුවය ලබයි",
       "News Content": "කොරෝනා ආසාදනය වී සිටි තවත් පුද්ගලයින් 243 දෙනෙකු සුවය ලබා රෝහල් වලින් පිටව ගොස් තිබෙනවා.\nඒ අනුව, සුවය ලැබූ මුළු ආසාදිත සංඛ්‍යාව 88,388 ක් ලෙසයි දැක්වෙන්නේ.\nකොරෝනා ආසාදිතයින් 2615 දෙනෙකු මේ වනවිට තවදුරටත් රෝහල් ගතව ප්‍රතිකාර ලබනවා.\nමෙරට කොරෝනා ආසාදිතයින් මුළු සංඛ්‍යාව 91,561 ක්.",
       "URL": "https://www.hirunews.lk/266711/තවත්-ආසාදිතයින්-243-දෙනෙකු-සුවය-ලබයි",
       "Category": "Local News",
       "Parent URL": "https://www.hirunews.lk/local-news.php?pageID=2059"
}