{
       "Source": "hirunews",
       "Timestamp": "Sunday, 14 May 2023 - 15:08",
       "Headline": "රේගුවේ ප්‍රමාදයන් වැළැක්වීමට සියලු පියවර ගත් බව මුදල් රාජ්‍ය ඇමති පවසයි",
       "News Content": "රේගුවේ සිදුවන ප්‍රමාද වැළැක්වීම සඳහා අවශ්‍ය සියලු පියවර ගෙන ඇති බව මුදල් රාජ්‍ය අමාත්‍ය රංජිත් සියඹලාපිටිය පවසනවා.\nරුවන්වැල්ල ප්‍රදේශයේදී මාධ්‍යයට අදහස් දක්වමින් අමාත්‍යවරයා පවසා සිටියේ කිසියම් පිරිසක් විසින් සැලසුම් සහගතව රේගුව තුල තදබදයක් ඇති කිරීමට කටයුතු කළ බවයි.\nවාප්පු නිලධාරින් සේවයට වාර්තා කිරීමේදී ඇති ප්‍රමාදයක් හේතුවෙන් රේගුවේ නිශ්කාශන කටයුතු වලට බලපෑම් එල්ල වී තිබුණා.\nපසුගිය සතිය වන විට නිශ්කාෂනයට නියමිත බහාලුම් රැසක් ඔරුගොඩවත්ත රේගු අංගනයේ සහ ඉන් පිටත ගොඩගැසී තිබූ බවටයි වාර්තා වුණේ.",
       "URL": "https://www.hirunews.lk/335164/රේගුවේ-ප්‍රමාදයන්-වැළැක්වීමට-සියලු-පියවර-ගත්-බව-මුදල්-රාජ්‍ය-ඇමති-පවසයි",
       "Category": "Local News",
       "Parent URL": "https://www.hirunews.lk/local-news.php?pageID=344"
}