{
       "Source": "hirunews",
       "Timestamp": "Wednesday, 01 March 2017 - 13:23",
       "Headline": "සබරගමුවේ වෛද්‍ය වර්ජනයෙන් රෝහල් කටයුතුවලට බාධා",
       "News Content": "මාළඹේ පෞද්ගලික වෛද්‍ය විද්‍යාලයට එරෙහිව රජයේ වෛද්‍ය නිලධාරින්ගේ සංගමය සබරගමුව පළාත තුල ආරම්භ කර ඇති වර්ජනය හේතුවෙන් රෝහල් කටයුතු අඩාල වී තිබෙනවා.\nපෙරවරු 8 ට ආරම්භ කෙරුණු මෙම වර්ජනය හෙට (02) පෙරවරු 8 දක්වා ක්‍රියාත්මකයි.",
       "URL": "https://www.hirunews.lk/155768/සබරගමුවේ-වෛද්‍ය-වර්ජනයෙන්-රෝහල්-කටයුතුවලට-බාධා",
       "Category": "Local News",
       "Parent URL": "https://www.hirunews.lk/local-news.php?pageID=4637"
}