{
       "Source": "hirunews",
       "Timestamp": "Thursday, 16 March 2023 - 14:55",
       "Headline": "සුබ සාධක ප්‍රතිලාභ අයදුම්පත් ගැන ෂෙහාන් සේමසිංහගෙන් මතක් කිරීමක්",
       "News Content": "ප්‍රාදේශීය ලේකම් කොට්ඨාස 334කින් ලද සුබ සාධක ප්‍රතිලාභ අයදුම්පත් මිලියන 3.7කින් තොරතුරු සමීක්ෂණ හා සත්‍යාපන ක්‍රියාවලිය මගින් ලද අයදුම්පත්වල තොරතුරුවල සත්‍යාපන කටයුතු මේ වනවිට (16) අවසන්කර ඇති බව මුදල් රාජ්‍ය අමාත්‍ය ෂෙහාන් සේමසිංහ පවසනවා.\nමෙම තොරතුරු සමීක්ෂණය මෙම මස 31 වැනි දිනට පෙර නිවැරදි තොරතුරු ලබාදෙන ලෙසයි රාජ්‍ය අමාත්‍යවරයා ඉල්ලා සිටින්නේ.\nඑසේ නොවුණහොත් සුබසාධක ප්‍රතිලාභ අහිමි වන බවට ද අමාත්‍යවරයා විසින් වැඩිදුරටත් අවධාරණය කරනු ලබනවා.",
       "URL": "https://www.hirunews.lk/330121/සුබ-සාධක-ප්‍රතිලාභ-අයදුම්පත්-ගැන-ෂෙහාන්-සේමසිංහගෙන්-මතක්-කිරීමක්",
       "Category": "Local News",
       "Parent URL": "https://www.hirunews.lk/local-news.php?pageID=472"
}