{"Source": "Adaderana", "Timestamp": "August 24, 2013 08:24 am", "Headline": "  මග මරුවාට කතක් බිලි", "News Content": "කොළඹ - මීගමුව ප්‍රධාන මාර්ගයේ දඩුගම පාලම අසල දී සිදුවු රිය අනතුරකින් කාන්තාවක ජීවිතක්ෂයට පත්වී තිබේ. ලොරි රථයක් යතුරු පැදියක ගැටීමෙන් අනතුර සිදුව ඇති බව පොලීසිය පැවසුවේය. අනතුරෙන් බරපතළ තුවාල ලැබු යතුරුපැදියේ ගමන්ගත් කාන්තාව සීදුව රෝහලට ඇතුළත් කිරීමෙන් අනතුරුව ඇය වැඩිදුර ප්‍රතිකාර සඳහා රාගම රෝහල වෙත රැගෙන යන අවස්ථාවේ මියගොස් ඇත. මියගොස් ඇත්තේ 35 හැවිරිදි හෙට්ටිපොල ප්‍රදේශයේ පදිංචි කාන්තාවකි. සිද්ධියෙන් සම්බන්ධයෙන් ලොරි රථයේ රියදුරු අත්අඩංගුවට ගෙන ඇති අතර ඔහු අද මීගමුව මහේස්ත්‍රාත් අධිකරණය වෙත ඉදිරිපත් කිරීමට නියමිතය.", "URL": "https://sinhala.adaderana.lk/news.php?nid=36854", "Category": null, "Parent URL": null}