{
       "Source": "hirunews",
       "Timestamp": "Sunday, 02 February 2020 - 18:42",
       "Headline": "විස්සයි විස්ස පහේම ජය ඉන්දියාවට",
       "News Content": "නවසීලන්තය සමඟ පැවති 5 වන සහ අවසාන විස්සයි විස්ස ජාත්‍යන්තර තරඟයෙන් ද ලකුණු 7ක ජයග්‍රහණයක් වාර්තා කිරීමට සංචාරක ඉන්දීය පිළ අද (02) සමත් වුණා.\nමවුන්ට් මංගනුයි හි පැවති එම තරඟයේදී කාසියේ වාසිය දිනා පළමුවෙන් පන්දුවට පහර දුන් ඉන්දීය පිළ සිය පන්දු වාර 20 තුළ දී කඩුලු 03ක් දැවී ලකුණු 163ක් රැස් කළා.\nපිළිතුරු වශයෙන් නවසීලන්ත පිළට සිය පන්දු වාර 20 තුළදී කඩුලු  09ක් දැවී රැස් කර ගත හැකි වූයේ ලකුණු 156ක් පමණයි.\nමේ අනුව නවසීලන්තය සමඟ පැවති විස්සයි විස්ස ජාත්‍යන්තර තරඟාවලිය ඉන්දියාව 05ට බින්දුවක් ලෙස ජයග්‍රහණය කරනු ලබනවා.\nඉන් තරඟ 02කම ජය සුපිරි  ඕවරයෙන් තීරණය වීම විශේෂත්වයක්.",
       "URL": "https://www.hirunews.lk/sports/233573/විස්සයි-විස්ස-පහේම-ජය-ඉන්දියාවට",
       "Category": "Sports",
       "Parent URL": "https://www.hirunews.lk/sports/all-news.php?pageID=115"
}