{
       "Source": "divaina",
       "Timestamp": "October 19, 2022",
       "Headline": "වෙඩි වැදී තරුණියක් මරුට",
       "News Content": "වව්නියාව, නෙඩුන්කේනි, ශිවානගර් ප්‍රදේශයේදී ඊයේ රාත්‍රියේ 8.30 ට පමණ සිදුවු වෙඩිතැබීමකින් වයස අවුරුදු 21ක තරුණියක් ජීවිතක්ෂයට පත්ව ඇති බව නෙඩුන්කේනි පොලීසිය පවසයි.පොලීසිය පැවසූවේ, නෙඩුන්කේනි, ශිවානගර් ප්‍රදේශයේම පදිංචි දුරෙයිරාජසිංහම් ප්‍රමිලා නමැති 21 හැවිරිදි තරුණියක් වෙඩිවැදීමෙන් ජිවිතක්ෂයට පත්ව ඇති බවය.",
       "URL": "https://divaina.lk/%e0%b7%80%e0%b7%99%e0%b6%a9%e0%b7%92-%e0%b7%80%e0%b7%90%e0%b6%af%e0%b7%93-%e0%b6%ad%e0%b6%bb%e0%b7%94%e0%b6%ab%e0%b7%92%e0%b6%ba%e0%b6%9a%e0%b7%8a-%e0%b6%b8%e0%b6%bb%e0%b7%94%e0%b6%a7/",
       "Category": "vigasa-puwath",
       "Parent URL": "https://divaina.lk/category/vigasa-puwath//page/483/"
}