{
    "Source": "www.lankadeepa.lk",
    "Timestamp": "а¶ҡа¶ӯа·ҳ а¶ёа¶«а·Ҡа¶©а¶Ҫа¶ә  2018 а¶ёа·җа¶әа·’ а¶ёа·ғ 08",
    "Headline": "а¶»а·Ҹа¶ўа·’а¶ӯ а¶Ҝа·җа·Җ а·ға¶Ӯа·ға·Ҡа¶®а·Ҹ а·ға¶·а·Ҹа¶ҙа¶ӯа·’а¶§ а·ға·„а¶ӯа·’а¶ҡа¶әа¶ҡа·Ҡ а¶Ҝа·ҷа¶ұа·Ҡа¶ұ а¶әа¶әа·’",
    "News Content": "(а·Җа·’а¶ұа·“а¶ӯа·Ҹ а¶‘а¶ёа·Ҡ а¶ңа¶ёа¶ңа·ҡ)а¶»а·Ҹа¶ўа·Ҡ‍а¶ә  а¶Ҝа·җа·Җ а·ға¶Ӯа·ға·Ҡа¶®а·Ҹа·Җа·ҡ а¶ұа·Җ а·ға¶·а·Ҹа¶ҙа¶ӯа·’а·Җа¶»а¶әа·Ҹ а¶Ҫа·ҷа·ғ а¶ҙа¶ӯа·Ҡа¶ҡа¶» а¶Үа¶ӯа·’ а¶ӯа·җа¶ұа·җа¶ӯа·Ҡа¶ӯа·Ҹ а¶ҙа·’а·…а·’а¶¶а¶іа·Җ а¶ўа¶ұа·Ҹа¶°а·’а¶ҙа¶ӯа·’а·Җа¶»а¶әа·Ҹ а·ға¶ёа¶ҹ а·ға·Ҹа¶ҡа¶ а·Ҡа¶Ўа·Ҹ а¶ҡа·’а¶»а·“а¶ёа¶§ а¶¶а¶Ҫа·Ҹа¶ҙа·ңа¶»а·ңа¶ӯа·Ҡа¶ӯа·” а·Җа¶ұ а¶¶а·Җ а·ға·һа¶ӣа·Ҡ‍а¶ә а¶ҙа·қа·Ӯа¶« а·„а·Ҹ а¶Ҝа·ҡа·Ға·“а¶ә а·Җа·ӣа¶Ҝа·Ҡ‍а¶ә а¶…а¶ёа·Ҹа¶ӯа·Ҡ‍а¶ә а¶Ҝа·ңа·ға·Ҡа¶ӯа¶» а¶»а·Ҹа¶ўа·’а¶ӯ а·ға·ҡа¶ұа·Ҹа¶»а¶ӯа·Ҡа¶ұ а¶ёа·„а¶ӯа·Ҹ а¶ҙ‍а·Ҡ‍а¶»а¶ҡа·Ҹа·Ғ  а¶ҡа·…а·ҡа¶ә.а¶…а¶Ҫа·Ҡа¶Ҫа·ға·Ҡ а·ға·’а¶Ҝа·Ҡа¶°а·’а¶әа¶ҡа·Ҡ а¶ёа¶ӯ а¶…а¶ӯа·Ҡа¶…а¶©а¶Ӯа¶ңа·”а·Җа¶§ а¶ңа¶ӯа·Ҡ а¶ўа¶ұа·Ҹа¶°а·’а¶ҙа¶ӯа·’ а¶ҡа·Ҹа¶»а·Ҡа¶әа¶ёа¶«а·Ҡа¶©а¶Ҫ а¶ҙ‍а·Ҡ‍а¶»а¶°а·Ҹа¶ұа·’а¶әа·Ҹ а¶‘а¶ё а¶ӯа¶ұа¶ӯа·”а¶»а·ҡ а·ға·’а¶§а·’а¶ұ а¶¶а·Җ а¶ӯа¶ёа¶ұа·Ҡ а¶Ҝа¶ұа·Ҡа¶ұа·ҡ а¶”а·„а·” а¶…а¶ӯа·Ҡ а¶…а¶©а¶Ӯа¶ңа·”а·Җа¶§ а¶ҙа¶ӯа·Ҡа·Җа·“а¶ёа·ҷа¶ұа·Ҡ а¶ҙа·ға·”а·Җ а¶әа·җа¶әа·’ а¶Ҝ а·„а·ҷа¶ӯа·ҷа¶ё а·ға¶іа·„а¶ұа·Ҡ а¶ҡа·…а·ҡа¶ә. а¶ӯа¶ёа¶ұа·Ҡ а¶үа¶©а¶ёа·Ҡ а¶…а¶ёа·Ҹа¶ӯа·Ҡ‍а¶әа·Җа¶»а¶әа·Ҹ а¶Ҫа·ҷа·ғ а¶ҡа¶§а¶әа·”а¶ӯа·” а¶ҡа¶»а¶Ҝа·Ҡа¶Ҝа·“ а¶‘а¶ё а¶…а¶ёа·Ҹа¶ӯа·Ҡ‍а¶әа¶Ӯа·Ға¶әа·ҡ а¶Ҫа·ҡа¶ҡа¶ёа·Ҡа·Җа¶»а¶әа·Ҹ а¶Ҫа·ҷа·ғ а¶ёа·„а·Ҹа¶ұа·Ҹа¶ё а¶ёа·„а¶ӯа·Ҹ а¶ҡа¶§а¶әа·”а¶ӯа·” а¶ҡа·… а¶¶а·Җ а¶Ҝ а·„а·ҷа¶ӯа·ҷа¶ё а¶ҡа·’а¶әа·Ҹ а·ға·’а¶§а·’а¶әа·ҡа¶ә.  а¶‘а·Җа¶ҡа¶§ а¶ёа·”а¶Ҫа·Ҡа¶Ҫа·ҡа¶»а·’а¶әа·Ҹа·Җа·ҡ а¶»а·қа·„а¶Ҫа¶§ а¶әа·Ҹа¶¶а¶Ҝ а·Җ а¶ӯа·’а¶¶а·” а¶үа¶©а¶ёа¶ҡа·Ҡ а¶ а·ңа¶ҡа·Ҡа¶Ҫа¶§а·Ҡ а·ға¶ёа·Ҹа¶ңа¶ёа¶ҡа¶§ а¶Ҝа·“ а¶ӯа·’а¶¶а·” а·ға·’а¶Ҝа·Ҡа¶°а·’а¶әа¶ҡа·Ҡ а·ға·’а·„а·’а¶ҙа¶ӯа·Ҡ а¶ҡа·… а¶…а¶ёа·Ҹа¶ӯа·Ҡ‍а¶әа·Җа¶»а¶әа·Ҹ а¶‘а·„а·’ а¶ңа·’а·Җа·’а·ға·”а¶ё а¶…а·Җа·ға¶ұа·Ҡа·Җ а¶ӯа·’а¶¶а·’а¶әа¶Ҝа·“а¶ӯа·Ҡ а¶‘а¶ә а¶әа·…а·’ а¶ҙа·Җа¶»а·Ҹа¶ңа¶ұа·Ҡа¶ұа¶§ а¶ңа·’а¶ә а¶…а·Җа·ға·Ҡа¶®а·Ҹа·Җа·ҡ а¶Ҫа·ҡа¶ҡа¶ёа·Ҡа·Җа¶»а¶әа·Ҹ  а·ға¶ёа·Ҹа¶ңа¶ё а·Җа·ҷа¶ұа·”а·Җа·ҷа¶ұа·Ҡ  а¶ҙа·ҷа¶ұа·“ а·ға·’а¶§а·’а¶әа·ҡ а¶әа·җа¶әа·’ а¶Ҝ а·ға·’а·„а·’а¶ҙа¶ӯа·Ҡ а¶ҡа·…а·ҡа¶ә. а¶”а·„а·” а·ға¶ёа·Ҹа¶ңа¶ёа·Ҡ а·„а·Ҹ а·ға¶ёа·“а¶ҙа·Җ а¶ҡа¶§а¶әа·”а¶ӯа·” а¶ҡа·… а¶¶а·Җ а¶‘а·Җа¶ҡ  а¶ҙа¶§а¶ұа·Ҡа¶ё а¶ӯа¶ёа¶ұа·Ҡ а·Җа¶§а·„а·Ҹ а¶ңа·ҷа¶ұ а·ға·’а¶§а·’а¶әа·ҡ  а¶әа·җа¶әа·’ а¶Ҝ а¶”а·„а·” а¶ӯа·Җа¶Ҝа·”а¶»а¶§а¶ӯа·Ҡ а¶ҙа·җа·Җа·җа·ға·”а·Җа·ҡа¶ә. а¶…а¶Ҫа·Ҡа¶Ҫа·ға·Ҡ а·ға·’а¶Ҝа·Ҡа¶°а·’а¶ә а¶ёа¶ӯ а¶”а·„а·” а·ға¶ёа¶ҹ а¶…а¶ӯа·Ҡа¶…а¶©а¶Ӯа¶ңа·”а·Җа¶§ а¶ҙа¶ӯа·Ҡ а¶Ҝа·җа·Җ а·ға¶Ӯа·ға·Ҡа¶®а·Ҹа·Җа·ҡ а·„а·’а¶§а¶ҙа·” а·ға¶·а·Ҹа¶ҙа¶ӯа·’а·Җа¶»а¶әа·Ҹ а¶ӯа¶ёа¶ұа·Ҡа¶§ а¶‘а¶»а·ҷа·„а·’а·Җ а¶…а¶Ҫа·Ҡа¶Ҫа·ға·Ҡ а¶ҡа·ңа¶ёа·’а·ға¶ё а¶үа¶Ҝа·’а¶»а·’а¶әа¶§  а¶ңа·’а¶ә а¶ҙа·”а¶Ҝа·Ҡа¶ңа¶Ҫа¶әа·Ҹ а¶әа·җа¶әа·’ а¶Ҝ а·„а·ҷа¶ӯа·ҷа¶ё а¶ҡа·’а¶әа·Ҹ а·ға·’а¶§а·’а¶әа·ҡа¶ә. а¶…а¶ёа·Ҹа¶ӯа·Ҡ‍а¶әа·Җа¶»а¶әа·Ҹ а¶ёа·ҡ а¶¶а·Җ а¶ҡа·’а¶әа·Ҹ а·ға·’а¶§а·’а¶әа·ҡ а¶»а¶ўа¶әа·ҡ а¶ҙ‍а·Ҡ‍а¶»а·Җа·ҳа¶ӯа·Ҡа¶ӯа·’ а¶Ҝа·ҷа¶ҙа·Ҹа¶»а·Ҡа¶ӯа¶ёа·ҡа¶ұа·Ҡа¶ӯа·”а·Җа·ҡ а¶…а¶Ҝ (8) а¶ҙа·җа·Җа·җа¶ӯа·’ а¶ёа·Ҹа¶°а·Ҡ‍а¶ә а·„а¶ёа·”а·Җа¶ҡ а¶Ҝа·“ а¶ёа·Ҹа¶°а·Ҡ‍а¶әа·Җа·ҡа¶Ҝа·’а¶әа¶ҡа·” а¶ұа·җа¶ңа·– а¶ҙа·җа¶ұа¶әа¶ҡа¶§ а¶ҙа·’а·…а·’а¶ӯа·”а¶»а·” а¶Ҝа·ҷа¶ёа·’а¶ұа·’.   ",
    "URL": "https://www.lankadeepa.lk/latest_news/රාජිත-දැව-සංස්ථා-සභාපතිට-සහතිකයක්-දෙන්න-යයි/1-528581",
    "Category": "latest_news"
}