{
    "Source": "www.lankadeepa.lk",
    "Timestamp": "None  2016 а¶ўа·”а¶Ҫа·’ а¶ёа·ғ 06",
    "Headline": "вҖҳвҖҳа¶¶а¶Ҫа·Ҡа¶Ҫа¶ұа·Ҡа¶§ а¶¶а¶Ҝа·” а¶ңа·„а¶Ҝа·Ҡа¶Ҝа·’ а¶¶а·җа·ға·’а¶Ҫа·Ҡ а¶ҡа·…а¶¶а·… а·Җа·ҷа¶ұа·Ҡа¶ұа·ҡ а¶Үа¶әа·’?вҖҳвҖҳ",
    "News Content": "а¶ҡа·җа¶¶а·’а¶ұа¶§а·Ҡ а¶ӯа·“а¶»а¶« а¶Ҝа·җа¶ұа·”а¶ёа·Ҡ а¶Ҝа·’а¶ёа·ҡ а¶ёа·Ҹа¶°а·Ҡ‍а¶ә а·ға·Ҹа¶ҡа¶ а·Ҡа¶Ўа·Ҹа·Җ а¶»а¶ўа¶әа·ҡ а¶ҙа·Ҡ‍а¶»а·Җа·ҳа¶ӯа·Ҡа¶ӯа·’ а¶Ҝа·ҷа¶ҙа·Ҹа¶»а·Ҡа¶ӯа¶ёа·ҡа¶ұа·Ҡа¶ӯа·”а·Җа·ҡ а¶Ҝа·“ а¶…а¶Ҝ а¶ҙа·җа·Җа·җа¶ӯа·Ҡа·Җа·’а¶«а·’.а¶’ а·ға¶іа·„а·Ҹ а¶ҡа·җа¶¶а·’а¶ұа¶§а·Ҡ а¶ҙа·Ҡ‍а¶»а¶ҡа·Ҹа·Ға¶ҡа¶әа¶ұа·Ҡ а·Җа¶ұ а¶Үа¶ёа·җа¶ӯа·’ а¶Ҝа·ңа·ға·Ҡа¶ӯа¶» а¶»а·Ҹа¶ўа·’а¶ӯ а·ға·ҡа¶ұа·Ҹа¶»а¶ӯа·Ҡа¶ұ а·ға·„ а¶Үа¶ёа·җа¶ӯа·’ а¶ңа¶әа¶ұа·Ҡа¶ӯ а¶ҡа¶»а·”а¶«а·Ҹа¶ӯа·’а¶Ҫа¶ҡ а¶ёа·„а¶ӯа·Ҡа·Җа¶»а·”а¶ұа·Ҡа¶§ а¶…а¶ёа¶ӯа¶»а·Җ а¶ұа·’а¶әа·қа¶ўа·Ҡ‍а¶ә а¶Үа¶ёа·җа¶ӯа·’а·Җа¶»а·”а¶ұа·Ҡ а·Җа¶ұ а¶ҡа¶»а·” а¶ҙа¶»а¶«а·Җа·’а¶ӯа·Ҹа¶ұ а·ға·„ а¶‘а¶»а·Ҹа¶ұа·Ҡ а·Җа·’а¶ҡа·Ҡ‍а¶»а¶ёа¶»а¶ӯа·Ҡа¶ұ а¶ёа·„а¶ӯа·Ҡа·Җа¶»а·” а¶Ҝ, а¶ҙа·Ҡ‍а¶»а·Җа·ҳа¶ӯа·Ҡа¶ӯа·’ а¶…а¶°а·Ҡ‍а¶әа¶ҡа·Ҡа·Ӯ а¶ўа¶ұа¶»а·Ҹа¶Ҫа·Ҡ а¶»а¶Ӯа¶ң а¶ҡа¶Ҫа¶Ӯа·ға·–а¶»а·’а¶ә, а·„а¶ёа·”а¶Ҝа·Ҹ а¶ҙа·Ҡ‍а¶»а¶ҡа·Ҹа·Ға¶ҡ а¶¶а·Ҡ‍а¶»а·’а¶ңа·ҡа¶©а·’а¶әа¶»а·Ҡ а¶ўа¶әа¶ұа·Ҹа¶ӯа·Ҡ а¶ўа¶әа·Җа·“а¶» а¶ёа·„а¶ӯа·Ҡа·Җа¶»а·” а¶Ҝ а¶ҙа·җа¶ёа·’а¶« а·ға·’а¶§а·’а¶әа·„.а·ға·”а¶ҙа·”а¶»а·”а¶Ҝа·” а¶ҙа¶»а·’а¶Ҝа·’ а¶ҡа¶»а·”а¶«а·Ҹа¶ӯа·’а¶Ҫа¶ҡ а¶ёа·„а¶ӯа·Ҹ а¶ҡа·җа¶¶а·’а¶ұа¶§а·Ҡ а¶ӯа·“а¶»а¶« а¶ҡа·ҷа¶§а·’а¶әа·ҷа¶ұа·Ҡ а¶ҙа·җа·„а·җа¶Ҝа·’а¶Ҫа·’ а¶ҡа·…а·ҡа¶ә.  а¶үа¶ұа·Ҡ а¶ҙа·ға·” а·Җа·җа¶§а·Ҡ а¶¶а¶Ҝа·” а·Җа·җа¶©а·’а¶ҡа·’а¶»а·“а¶ё а·ға¶ёа·Ҡа¶¶а¶ұа·Ҡа¶°а¶әа·ҷа¶ұа·Ҡ а¶ұа·’а¶әа·қа¶ўа·Ҡ‍а¶ә а¶Үа¶ёа·җа¶ӯа·’ а¶‘а¶»а·Ҹа¶ұа·Ҡа¶§ а¶Ҷа¶»а·Ҹа¶°а¶ұа·Ҹ а¶ҡа·… а¶ңа·„а¶ұа·Ҡа¶ӯ а¶Үа¶ёа·җа¶ӯа·’а·Җа¶»а¶әа·Ҹ а¶ҡа·“а·Җа·ҡ ‘а¶”а·„а·”а¶ңа·ҡ а¶ҡа¶ӯа·Ҹа·Җа·ҷа¶ұа·Ҡ а¶ҙа·ға·” а¶»а·Ҹа¶ўа·’а¶ӯ а¶Үа¶ёа·җа¶ӯа·’а¶ӯа·”а¶ёа·Ҹ а·ға·”а¶ҙа·”а¶»а·”а¶Ҝа·”а¶ҙа¶»а·’а¶Ҝа·’ а¶үа¶ӯа·”а¶»а·”а¶§а·’а¶ҡ а¶¶а¶Ҫа·Ҹа¶ңа¶ұа·’а¶әа·’.‘ а¶әа·җа¶әа·’ а¶ҡа·’а¶әа¶Ҝа·Ҡа¶Ҝа·“ а·ға·’а¶әа¶Ҫа·” а¶Ҝа·ҷа¶ұа·Ҹа¶ё а·ға·’а¶ұа·Ҹ а·ға·”а¶ұа·„.а¶Үа¶ёа·җа¶ӯа·’а·Җа¶»а·”а¶ұа·Ҡа¶ңа·ҡ а¶ҡа¶ӯа·Ҹ а·Җа¶Ҫа·’а¶ұа·Ҡ а¶ҙа·ға·” а¶ёа·Ҹа¶°а·Ҡ‍а¶әа·Җа·ҡа¶Ҝа·“а¶ұа·Ҡ а¶ҙа·Ҡ‍а¶»а·Ға·Ҡа¶ұ а¶…а·ға¶ұа·Ҡа¶ұа¶§ а¶ҙа¶§а¶ұа·Ҡ а¶ңа¶ӯа·Ҡа¶ӯа·ҡа¶ә.а¶¶а·җа·ға·’а¶Ҫа·Ҡ а¶»а·Ҹа¶ўа¶ҙа¶ҡа·Ҡа·Ӯ а·„а·’а¶§а¶ҙа·” а¶Үа¶ёа·җа¶ӯа·’а·Җа¶»а¶әа·Ҹ а¶ҡа·…а·җа¶әа·’ а¶ҡа·’а¶әа¶ұ а¶ҙа·Ҡ‍а¶»а¶ҡа·Ҹа·Ға¶әа¶ҡа·Ҡ а·ға¶ёа·Ҡа¶¶а¶ұа·Ҡа¶°а¶әа·ҷа¶ұа·Ҡ а¶ҙа·Ҡ‍а¶»а·Ға·Ҡа¶ұ а¶әа·ңа¶ёа·” а¶ҡа·җа¶»а¶«а·’.а¶ёа·Ҹа¶°а·Ҡ‍а¶әа·Җа·ҡа¶Ҝа·’а¶әа·ҷа¶ҡа·Ҡ - а¶¶а·җа·ға·’а¶Ҫа·Ҡ а¶»а·Ҹа¶ўа¶ҙа¶ҡа·Ҡа·Ӯ а¶Үа¶ёа·җа¶ӯа·’а·Җа¶»а¶әа·Ҹ а¶ҡа·’а¶әа·Ҹ а¶ӯа·’а¶¶а·”а¶«а·Ҹ а¶ёа·ҡ а¶Ҷа¶«а·Ҡа¶©а·”а·Җ а¶¶а¶Ҫа·” а¶¶а¶Ҝа·Ҡа¶Ҝ а·ға·„ а¶Үа¶ң а¶¶а¶Ҝа·Ҡа¶Ҝа¶ӯа·Ҡ а¶ңа·„а¶ұа·Ҡа¶ұ а¶әа¶ұ а¶¶а·Җ.а¶‘а¶ё а¶ҙа·Ҡ‍а¶»а·Ға·Ҡа¶ұа¶§ а¶ҙа·’а·…а·’а¶ӯа·”а¶»а·” а¶Ҝа·“а¶ёа¶§ а¶ұа·’а¶әа·қа¶ўа·Ҡ‍а¶ә а¶Үа¶ёа·җа¶ӯа·’ а¶ҡа¶»а·” а¶ҙа¶»а¶«а·Җа·’а¶ӯа·Ҹа¶ұ а¶ёа·„а¶ӯа·Ҹ а·ға·–а¶Ҝа·Ҹа¶ұа¶ёа·Ҡ а·Җа·ҷа¶Ҝа·Ҡа¶Ҝа·“а¶ё а¶Ҝа·ңа·ға·Ҡа¶ӯа¶» а¶»а·Ҹа¶ўа·’а¶ӯ а·ға·ҡа¶ұа·Ҹа¶»а¶ӯа·Ҡа¶ұ а¶ёа·„а¶ӯа·Ҹ а¶Ҡа¶§ а¶үа·ға·Ҡа·ға¶» а·Җа·’а¶ә.а¶»а·Ҹа¶ўа·’а¶ӯ а·ға·ҡа¶ұа·Ҹа¶»а¶ӯа·Ҡа¶ұ - а¶¶а¶Ҫа·Ҡа¶Ҫа¶ұа·Ҡа¶§ а¶¶а¶Ҝа·” а¶ңа·„а¶ұа¶ҡа·ңа¶§ а¶¶а·җа·ға·’а¶Ҫа·Ҡ а¶Үа¶ёа·җа¶ӯа·’а¶ӯа·”а¶ёа·Ҹ а¶Үа¶әа·’ а¶”а¶ а·Ҡа¶ а¶» а¶ҡа·…а¶¶а¶Ҫ а·Җа·ҷа¶ұа·Ҡа¶ұа·ҡ?а¶әа·…а·’ а¶ҡа¶»а·” а¶ҙа¶»а¶«а·Җа·’а¶ӯа·Ҹа¶ұ а¶ёа·„а¶ӯа·Ҹ а¶ҡа¶ӯа·Ҹ а¶ҡа¶»а¶ұа·Ҡа¶ұа¶§ а¶Ӣа¶ӯа·Ҡа·ға·Ҹа·„ а¶Ҝа¶»а¶Ҝа·Ҡа¶Ҝа·“ ‘а¶…а¶ұа·’а¶ӯа·Ҡ а¶ҡа·’а·ға·’ а¶Ҝа·ҡа¶ҡа¶§ а¶ҡа·…а¶¶а¶Ҫ а·Җа·”а¶«а·ҡ а¶ұа·җа¶ӯа·’ а¶‘а¶ҡа·Ҡа¶ҡа·ҷа¶ұа·Ҹ а¶Үа¶әа·’ а¶¶а¶Ҫа·Ҡа¶Ҫа¶ұа·Ҡа¶§ а¶ңа·„а¶Ҝа·Ҡа¶Ҝа·’ а¶ҡа·…а¶¶а¶Ҫ а·Җа·ҷа¶ұа·Ҡа¶ұа·ҡ?‘ а¶әа·җа¶әа·’ а¶әа·…а·’ а¶»а·Ҹа¶ўа·’а¶ӯ а·ға·ҡа¶ұа·Ҹа¶»а¶ӯа·Ҡа¶ұ а¶ёа·„а¶ӯа·Ҹ а¶ҡа·“а·Җа·ҡ а·ға·’а¶әа¶Ҫа·” а¶Ҝа·ҷа¶ұа·Ҹа¶§ а·ға·’а¶ұа·Ҹ а¶ұа¶Ӯа·Җа¶ёа·’а¶ұа·’.а¶ҡа¶»а·” а¶ҙа¶»а¶ұа·Җа·’а¶ӯа·Ҹа¶ұ - а¶ёа·ҡ а¶Ҷа¶«а·Ҡа¶©а·”а·Җ а¶¶а¶Ҫа·” а¶¶а¶Ҝа·Ҡа¶Ҝа¶ҡа·Ҡ а¶ңа·„а¶Ҫа¶ӯа·Ҡ а¶ұа·‘. а¶Үа¶ҹ а¶¶а¶Ҝа·Ҡа¶Ҝа¶ҡа·Ҡ а¶ңа·„а¶Ҫа¶ӯа·Ҡ а¶ұа·‘. а¶…а¶ӯа·Ҡ‍а¶әа·Җа·Ға·Ҡ‍а¶ә а¶·а·Ҹа¶«а·Ҡа¶© а·Җа¶Ҫа¶§ а¶¶а¶Ҝа·” а¶ңа·„а¶Ҫа¶ӯа·Ҡ а¶ұа·‘. а¶¶а¶Ҫа·” а¶¶а¶Ҝа·Ҡа¶Ҝ а¶ңа·җа·„а·”а·Җа·ҡ а¶¶а·җа·ға·’а¶Ҫа·Ҡ а¶»а·Ҹа¶ўа¶ҙа¶ҡа·Ҡа·Ӯа¶Ҫа·Ҹ а¶ӯа¶ёа¶әа·’. а¶¶а¶Ҫа·Ҡа¶Ҫа·” а¶ңа·ҷа¶ұа¶ӯа·Ҡ а¶¶а¶Ҫа·Ҡа¶Ҫа·ң а¶¶а¶Ҫа·Ҹа¶ңа¶ұа·Ҡа¶ұ а¶ұа·Ҹа·Җа·’а¶ҡ а·„а¶ёа·”а¶Ҝа·Ҹа·Җа·ҷа¶ұа·Ҡ а¶Ҝа·җа¶ёа·Ҡа¶ёа·Ҹ. а¶»а¶ўа¶ҡа·Ҹа¶Ҫа·ҡ а¶¶а¶Ҝа·” а¶ңа·ҷа·Җа·Ҡа·Җа·” а·Ға·Ҡ‍а¶»а¶ёа¶әа·ҷа¶ұа·Ҡ. а¶ұа·Ҹа·Җа·’а¶ҡ а·„а¶ёа·”а¶Ҝа·Ҹа·Җа·ҷа¶ұа·Ҡ а¶¶а¶Ҫа·Ҡа¶Ҫа¶ұа·Ҡ а¶¶а¶Ҫа·Ҹ а¶ңа¶ұа·Ҡа¶ұ а·Ға·Ҡ‍а¶»а¶ёа¶ә а¶ңа¶ӯа·Ҡа¶ӯа·Ҹ а¶ҡа·’а¶әа¶ұа·Ҡа¶ұа·ҡ а¶¶а¶Ҫа·” а¶¶а¶Ҝа·Ҡа¶Ҝа¶ҡа·Ҡ а¶ңа·җа·„а·”а·Җа·Ҹ а¶ҡа·’а¶әа¶ұ а¶‘а¶ҡа¶әа·’. ",
    "URL": "https://www.lankadeepa.lk/latest_news/‘‘බල්ලන්ට-බදු-ගහද්දි-බැසිල්-කළබළ-වෙන්නේ-ඇයි-‘‘/1-434437",
    "Category": "latest_news"
}