{
    "Source": "www.lankadeepa.lk",
    "Timestamp": "None  2012 ජුලි මස 02",
    "Headline": "මුංගුලියා අල්ලයි",
    "News Content": "දෙවසරකට වැඩි කාලයක් අනුරාධපුර ශ්‍රාවස්තිපුරය හොල්ලාගෙන සිටි ‘මුංගුලියා‘ (25) අලියා අද නිර්වින්දනය කැර අල්ලා ඈත කැලෑවකට රැගෙන ගිය බව වනජිවි නිලධරයෝ කියති. මුංගුලියා අතින් කතුන් තිදෙනකු ඇතුළු හත්දෙනෙක් මරුමුවට පත්වූහ. වනජිවි නියෝජ්‍ය අධ්‍යක්ෂ දොස්තර  තාරක ප්‍රසාද් ගජදීර හා වයඹ වනජිවි කලාප බාර පශු වෛද්‍ය චන්දන ජයසිංහ මහත්වරුන් ප්‍රධාන කණ්ඩායමක් දින පහක් තිස්සේ අලියා අල්ලා ගැනීමට වෙහෙසුණාහ.  ",
    "URL": "https://www.lankadeepa.lk/latest_news/මුංගුලියා-අල්ලයි/1-51314",
    "Category": "latest_news"
}