{"Source": "Ada News", "Timestamp": "21 07 2022", "Headline": "තමා ගැන පරීක්ෂණයක් කරන්නැයි ජනපතිගෙන් ඉල්ලයි", "News Content": "තමාට එල්ලවන චෝදනා සම්බන්ධයෙන් කඩිනම් පරීක්ෂණයක් පවත්වන ලෙස හිටපු අමාත්‍ය නිමල් සිරිපාල ද සිල්වා මහතා ජනාධිපති රනිල් වික්‍රමසිංහ මහතාගෙන් අද (21දා) ඉල්ලා සිටියේය. ජපානයේ සමාගමකින් අල්ලස් ලබා ගැනීමට උත්සහ කළ බවට චෝදනා එල්ල වූ අවස්ථාවේ ස්වාධීන පරීක්ෂණයකට ඉඩ සලසා දෙමින් තමා අමාත්‍ය ධුරයෙන් ඉල්ලා අස් වූ බවද  හිටපු අමාත්‍යවරයා සඳහන් කළේ‍ය. ඇමතිකමක්  ගන්නවට වඩා මට අවශ්‍ය  මගේ නම පිරිසුදු  කරගන්නැයි  එම අවස්ථාවේදී හිටපු අමාත්‍යවරයා පැවසීය.  ", "URL": "https://www.ada.lk/0/0/0-395622", "Category": "Latest News", "Parent URL": null}